.landscape.yml
CHANGES.txt
LICENSE
MANIFEST.in
README.rst
docs_requirements.txt
setup.py
docs/Makefile
docs/make.bat
docs/source/conf.py
docs/source/index.rst
docs/source/xmlrpcssl.handlers.rst
docs/source/xmlrpcssl.rst
examples/client_ldap_xmlrpc_ssl_example.py
examples/server_ldap_xmlrpc_ssl_example.py
xmlrpcssl/__init__.py
xmlrpcssl/xmlrpcssl.py
xmlrpcssl.egg-info/PKG-INFO
xmlrpcssl.egg-info/SOURCES.txt
xmlrpcssl.egg-info/dependency_links.txt
xmlrpcssl.egg-info/not-zip-safe
xmlrpcssl.egg-info/requires.txt
xmlrpcssl.egg-info/top_level.txt
xmlrpcssl/handlers/__init__.py
xmlrpcssl/handlers/ldapHandler.py