Metadata-Version: 1.1
Name: xmlrpcssl
Version: 0.1.3
Summary: xmlrpc server with basic authentication and secured with ssl
Home-page: https://github.com/jonDel/xmlrpcssl
Author: Jonatan Dellagostin
Author-email: jdellagostin@gmail.com
License: GPLv3
Keywords: ssl secure https xmlrpc rpc xml ldap
Platform: UNKNOWN
Classifier: Development Status :: 3 - Alpha
Classifier: License :: OSI Approved :: GNU General Public License v3 (GPLv3)
Classifier: Programming Language :: Python :: 2.6
Classifier: Programming Language :: Python :: 2.7
Classifier: Topic :: Internet :: WWW/HTTP :: HTTP Servers
Classifier: Topic :: System :: Systems Administration :: Authentication/Directory
